helga_amazon_meta/__init__.py
helga_amazon_meta/plugin.py
helga_amazon_meta-1.1.0.dist-info/DESCRIPTION.rst
helga_amazon_meta-1.1.0.dist-info/METADATA
helga_amazon_meta-1.1.0.dist-info/RECORD
helga_amazon_meta-1.1.0.dist-info/WHEEL
helga_amazon_meta-1.1.0.dist-info/entry_points.txt
helga_amazon_meta-1.1.0.dist-info/metadata.json
helga_amazon_meta-1.1.0.dist-info/top_level.txt
helga_amazon_meta-1.1.0.dist-info/zip-safe
tests/__init__.py
tests/test_plugin.py
